{"id":"pop-series-7-singles","name":"POP Series 7 Singles Market Indicators","tcg":"pokemon","universe":"pop-series-7-singles","updatedAt":"2026-06-25","metrics":["advanceDeclineTrend","percentAboveTrend","trendHeat","floorStrength","spread","trendDispersion","netTrendBreadth","marketWeightedPercentAboveTrend","medianTrendHeat","weakFloorPercent"],"units":{"advanceDeclineTrend":"ratio","percentAboveTrend":"percent","trendHeat":"score","floorStrength":"score","spread":"percent","trendDispersion":"percent","netTrendBreadth":"percent","marketWeightedPercentAboveTrend":"percent","medianTrendHeat":"score","weakFloorPercent":"percent"},"composition":{"universeFile":"/data/pokemon/universes/pop-series-7-singles-universe.json","universePolicy":"fixed-curated","currentBaseDate":"2026-06-23","rebalanceCount":0},"diagnostics":{"2026-06-23":{"activeProducts":17,"validProducts":17,"unavailableOrInvalidProducts":0,"trendBreadth":{"aboveTrend":12,"belowTrend":5,"equalTrend":0},"rebalance":false,"rebalanceDetails":null},"2026-06-24":{"activeProducts":17,"validProducts":17,"unavailableOrInvalidProducts":0,"trendBreadth":{"aboveTrend":12,"belowTrend":5,"equalTrend":0},"rebalance":false,"rebalanceDetails":null},"2026-06-25":{"activeProducts":17,"validProducts":17,"unavailableOrInvalidProducts":0,"trendBreadth":{"aboveTrend":13,"belowTrend":4,"equalTrend":0},"rebalance":false,"rebalanceDetails":null}},"points":[["2026-06-23",2.4,70.59,112.72,35.24,68.32,20.05,41.18,87.95,105.6,82.35],["2026-06-24",2.4,70.59,113.72,41.89,63.69,20.72,41.18,87.86,105.6,82.35],["2026-06-25",3.25,76.47,115.97,41.53,64.15,20.33,52.94,89.87,115.53,82.35]]}
