{"id":"prismatic-evolutions-additionals-singles","name":"Prismatic Evolutions: Additionals Singles Market Indicators","tcg":"pokemon","universe":"prismatic-evolutions-additionals-singles","updatedAt":"2026-06-25","metrics":["advanceDeclineTrend","percentAboveTrend","trendHeat","floorStrength","spread","trendDispersion","netTrendBreadth","marketWeightedPercentAboveTrend","medianTrendHeat","weakFloorPercent"],"units":{"advanceDeclineTrend":"ratio","percentAboveTrend":"percent","trendHeat":"score","floorStrength":"score","spread":"percent","trendDispersion":"percent","netTrendBreadth":"percent","marketWeightedPercentAboveTrend":"percent","medianTrendHeat":"score","weakFloorPercent":"percent"},"composition":{"universeFile":"/data/pokemon/universes/prismatic-evolutions-additionals-singles-universe.json","universePolicy":"fixed-curated","currentBaseDate":"2026-06-23","rebalanceCount":1},"diagnostics":{"2026-06-23":{"activeProducts":209,"validProducts":107,"unavailableOrInvalidProducts":102,"trendBreadth":{"aboveTrend":31,"belowTrend":25,"equalTrend":51},"rebalance":false,"rebalanceDetails":null},"2026-06-24":{"activeProducts":209,"validProducts":107,"unavailableOrInvalidProducts":102,"trendBreadth":{"aboveTrend":32,"belowTrend":25,"equalTrend":50},"rebalance":false,"rebalanceDetails":null},"2026-06-25":{"activeProducts":209,"validProducts":107,"unavailableOrInvalidProducts":102,"trendBreadth":{"aboveTrend":34,"belowTrend":23,"equalTrend":50},"rebalance":false,"rebalanceDetails":null}},"points":[["2026-06-23",1.24,28.97,130.04,60.28,40.07,182.19,5.61,34.09,100,66.36],["2026-06-24",1.28,29.91,130.26,60.36,40.19,182.13,6.54,34.76,100,67.29],["2026-06-25",1.48,31.78,130.16,60.63,40.15,182.07,10.28,38.43,100,66.36]]}
