{"id":"scarlet-ex-singles","name":"Scarlet ex Singles Market Indicators","tcg":"pokemon","universe":"scarlet-ex-singles","updatedAt":"2026-06-24","metrics":["advanceDeclineTrend","percentAboveTrend","trendHeat","floorStrength","spread","trendDispersion","netTrendBreadth","marketWeightedPercentAboveTrend","medianTrendHeat","weakFloorPercent"],"units":{"advanceDeclineTrend":"ratio","percentAboveTrend":"percent","trendHeat":"score","floorStrength":"score","spread":"percent","trendDispersion":"percent","netTrendBreadth":"percent","marketWeightedPercentAboveTrend":"percent","medianTrendHeat":"score","weakFloorPercent":"percent"},"composition":{"universeFile":"/data/pokemon/universes/scarlet-ex-singles-universe.json","universePolicy":"fixed-curated","currentBaseDate":"2026-06-23","rebalanceCount":0},"diagnostics":{"2026-06-23":{"activeProducts":116,"validProducts":116,"unavailableOrInvalidProducts":0,"trendBreadth":{"aboveTrend":47,"belowTrend":46,"equalTrend":23},"rebalance":false,"rebalanceDetails":null},"2026-06-24":{"activeProducts":116,"validProducts":116,"unavailableOrInvalidProducts":0,"trendBreadth":{"aboveTrend":41,"belowTrend":51,"equalTrend":24},"rebalance":false,"rebalanceDetails":null}},"points":[["2026-06-23",1.02,40.52,127.39,58.36,44.61,279.44,0.86,33.79,100,41.38],["2026-06-24",0.8,35.34,125.33,58.53,43.63,279.6,-8.62,29,100,41.38]]}
