{"id":"southern-islands-singles","name":"Southern Islands Singles Market Indicators","tcg":"pokemon","universe":"southern-islands-singles","updatedAt":"2026-06-25","metrics":["advanceDecline","percentAbove30d","heat","dispersion","advanceDeclineTrend","percentAboveTrend","trendHeat","floorStrength","spread","trendDispersion"],"units":{"advanceDecline":"ratio","percentAbove30d":"percent","heat":"score","dispersion":"percent","advanceDeclineTrend":"ratio","percentAboveTrend":"percent","trendHeat":"score","floorStrength":"score","spread":"percent","trendDispersion":"percent"},"composition":{"universeFile":"/data/pokemon/universes/southern-islands-singles-universe.json","universePolicy":"fixed-curated","currentBaseDate":"2026-06-23","rebalanceCount":0},"diagnostics":{"2026-06-23":{"activeProducts":18,"validProducts":18,"unavailableOrInvalidProducts":0,"trendBreadth":{"aboveTrend":2,"belowTrend":16,"equalTrend":0},"rebalance":false,"rebalanceDetails":null,"windowValidProducts":18,"windowUnavailableOrInvalidProducts":0,"advanceDecline":{"advancers":8,"decliners":10,"unchanged":0}},"2026-06-24":{"activeProducts":18,"validProducts":18,"unavailableOrInvalidProducts":0,"trendBreadth":{"aboveTrend":5,"belowTrend":13,"equalTrend":0},"rebalance":false,"rebalanceDetails":null,"windowValidProducts":18,"windowUnavailableOrInvalidProducts":0,"advanceDecline":{"advancers":8,"decliners":10,"unchanged":0}},"2026-06-25":{"activeProducts":18,"validProducts":18,"unavailableOrInvalidProducts":0,"trendBreadth":{"aboveTrend":5,"belowTrend":13,"equalTrend":0},"rebalance":false,"rebalanceDetails":null,"windowValidProducts":18,"windowUnavailableOrInvalidProducts":0,"advanceDecline":{"advancers":8,"decliners":10,"unchanged":0}}},"points":[["2026-06-23",0.8,61.11,108.29,46.54,0.13,11.11,92.28,55.12,40.2,15.47],["2026-06-24",0.8,61.11,108.29,46.54,0.38,27.78,94.57,56.01,40.66,14.57],["2026-06-25",0.8,61.11,108.29,46.54,0.38,27.78,94.43,60.77,35.59,14.55]]}
