{"id":"30th-anniversary-celebration-singles-universe","tcg":"pokemon","kind":"set-singles-universe","name":"30th Anniversary Celebration","slug":"30th-anniversary-celebration","source":{"productsCreatedAt":"2026-06-22T12:09:07+0200","idExpansion":6514,"cardmarketExpansionName":"30th Anniversary Celebration","cardmarketExpansionUrl":null,"cardmarketExpansionCardCount":null},"curation":{"status":"local-catalog-name-inferred","method":"idExpansion-product-ids-with-nonsingles-name-inference","cardmarketProductCount":18,"note":"Generated from Cardmarket product catalog idExpansion membership and non-single product names because the expansion page could not be fetched locally."},"count":18,"entries":{"876872":"Bulbasaur [Leech Seed | MEP]","876873":"Charmander [Ember | MEP]","876874":"Squirtle [Bubble | MEP]","876875":"Turtwig [Razor Leaf]","876876":"Chimchar [Fury Swipes | MEP]","876877":"Piplup [Peck]","876878":"Rowlet [Tackle]","876879":"Litten [Fire Fang | MEP]","876880":"Popplio [Disarming Voice | MEP]","886583":"Chikorita [Razor Leaf | MEP]","886584":"Cyndaquil [Tackle]","886585":"Totodile [Bite]","886586":"Snivy [Vine Whip]","886587":"Tepig [Ember | MEP]","886588":"Oshawott [Razor Shell | MEP]","886589":"Grookey [Branch Poke | MEP]","886590":"Scorbunny [Double Kick]","886591":"Sobble [Water Gun | MEP]"},"metrics":["avg","low","trend"]}
