{"id":"double-blaze-singles-universe","tcg":"pokemon","kind":"set-singles-universe","name":"Double Blaze","slug":"double-blaze","source":{"productsCreatedAt":"2026-06-22T12:09:07+0200","idExpansion":3836,"cardmarketExpansionName":"Double Blaze","cardmarketExpansionUrl":null,"cardmarketExpansionCardCount":null},"curation":{"status":"local-catalog-name-inferred","method":"idExpansion-product-ids-with-nonsingles-name-inference","cardmarketProductCount":116,"note":"Generated from Cardmarket product catalog idExpansion membership and non-single product names because the expansion page could not be fetched locally."},"count":116,"entries":{"557356":"Oddish [Stun Spore | Seed Bomb]","557357":"Oddish [Hook]","557358":"Gloom [Irresistible Aroma | Drool]","557359":"Vileplume [Varied Pollen | Giant Bloom]","557360":"Venonat [Psybeam]","557361":"Venomoth [Assassin Flight | Poison Powder]","557362":"Reshiram & Charizard GX [Outrage | Flare Strike | Double Blaze GX]","557363":"Growlithe [Live Coal | Combustion]","557364":"Arcanine [Grand Flame | Heat Tackle]","557365":"Darumaka [Flame Charge | Flop]","557366":"Darmanitan [Find Wildfire | Flare Blitz]","557367":"Volcanion [Flare Starter | High-Heat Blast]","557368":"Litten [Singe]","557369":"Litten [Caturday | Big Bite]","557370":"Torracat [Fire Fang]","557371":"Incineroar [Strong Cheer | Flamethrower]","557372":"Salandit [Grass Fire]","557373":"Salazzle [Roast Reveal | Combustion]","557374":"Blacephalon [Blazer | Fireball Circus]","557375":"Poliwag [Round 'n' Round | Watering]","557376":"Poliwag [Call for Family]","557377":"Poliwhirl [Bubble | Knuckle Punch]","557378":"Poliwrath [Knuckle Punch | Swirly Rush]","557379":"Seel [Horn Attack]","557380":"Dewgong [Tail Whap | Dual Blizzard]","557381":"Krabby [Stampede | Vice Grip]","557382":"Kingler [Bubble Beam | Massive Rend]","557383":"Stunfisk [Raging Thunder | Electric Trap]","557384":"Muk & Alolan Muk GX [Severe Poison | Poison Absorption | Nasty Goo Mix GX]","557385":"Gastly [Swelling Spite | Will-O-Wisp]","557386":"Gastly [Smog]","557387":"Haunter [Sinister Fog]","557388":"Gengar [Shadow Pain | Twilight Poison]","557389":"Koffing [Foul Odor]","557390":"Weezing [Detention Gas | Splattering Sludge]","557391":"Mewtwo [Mind Report | Psyshock]","557392":"Mew [Bench Barrier | Psypower]","557393":"Misdreavus [Ominous Eyes]","557394":"Mismagius [Mysterious Message | Hypnoblast]","557395":"Espurr [Caturday | Ear Kinesis]","557396":"Meowstic [Caturday | Perplexing Eyes]","557397":"Marshadow & Machamp GX [Revenge | Hundred-Blows Impact | Acme of Heroism GX]","557398":"Diglett [Underground Work | Hook]","557399":"Dugtrio [Home Ground]","557400":"Cubone [Focus Energy | Beat]","557401":"Marowak [Bone Rush | Assault Boom]","557405":"Rhyhorn [Push Down]","557406":"Rhyhorn [Horn Attack | Boulder Crush]","557407":"Rhydon [Dirty Work | Horn Attack]","557408":"Rhyperior [Hefty Cannon | Break Ground]","557409":"Tyrogue [Bratty Kick]","557410":"Landorus [Linear Attack | Power Cyclone]","557411":"Crabrawler [Corkscrew Punch | Knuckle Blast]","557412":"Crabominable [Fight Alone | Magnum Punch]","557413":"Murkrow [Astonish]","557414":"Honchkrow GX [Ruler of the Night | Feather Storm | Unfair GX]","557415":"Spiritomb [Building Spite | Anguish Cry]","557416":"Sandile [Intimidating Fang | Gnaw]","557417":"Sandile [Grandiose Fangs]","557418":"Krokorok [Bite | Corner]","557419":"Krookodile [Chomp Chomp Panic | Crunch]","557420":"Jigglypuff [Ball Roll]","557421":"Wigglytuff [Orb Polish | Sleepy Ball]","557422":"Cleffa [Excitable Draw]","557423":"Cottonee [Expand]","557424":"Whimsicott GX [Fluffy Cotton | Energy Blow | Toy Box GX]","557425":"Meowth [Caturday | Tail Whap]","557426":"Persian [Gathering of Cats | Claw Slash]","557427":"Persian GX [Cat Walk | Vengeance | Slash Back GX]","557428":"Doduo [Peck | Double Peck]","557429":"Dodrio [Tri Attack | Accelerating Stab]","557430":"Porygon [Digicharge | Sharp Point]","557431":"Porygon [Quick Draw | Ram]","557432":"Porygon2 [Double Draw | Spinning Attack]","557433":"Porygon-Z [Crazy Code | Tantrum]","557434":"Snorlax [Lazy Eating | Big Counter]","557435":"Happiny [Playhouse Heal]","557436":"Chatot [Mimic | Tone-Deaf]","557437":"Escape Rope","557438":"Chip-Chip Ice Axe","557439":"Ultra Ball","557440":"Rare Candy","557441":"Fire Crystal","557442":"Dusk Stone","557443":"Giovanni's Exile","557444":"Pokémon Fan Club","557445":"Welder","557446":"Red's Challenge","557447":"Martial Arts Dojo","557448":"Dust Island","557449":"Triple Acceleration Energy","557450":"Fiery Flint","557451":"Rescue Stretcher","557452":"Kiawe","557453":"Cynthia","557454":"Reshiram & Charizard GX [Outrage | Flare Strike | Double Blaze GX]","557455":"Reshiram & Charizard GX [Outrage | Flare Strike | Double Blaze GX]","557456":"Muk & Alolan Muk GX [Severe Poison | Poison Absorption | Nasty Goo Mix GX]","557457":"Muk & Alolan Muk GX [Severe Poison | Poison Absorption | Nasty Goo Mix GX]","557458":"Marshadow & Machamp GX [Revenge | Hundred-Blows Impact | Acme of Heroism GX]","557459":"Marshadow & Machamp GX [Revenge | Hundred-Blows Impact | Acme of Heroism GX]","557460":"Honchkrow GX [Ruler of the Night | Feather Storm | Unfair GX]","557461":"Whimsicott GX [Fluffy Cotton | Energy Blow | Toy Box GX]","557462":"Persian GX [Cat Walk | Vengeance | Slash Back GX]","557463":"Giovanni's Exile","557464":"Welder","557465":"Red's Challenge","557466":"Reshiram & Charizard GX [Outrage | Flare Strike | Double Blaze GX]","557467":"Muk & Alolan Muk GX [Severe Poison | Poison Absorption | Nasty Goo Mix GX]","557468":"Marshadow & Machamp GX [Revenge | Hundred-Blows Impact | Acme of Heroism GX]","557469":"Honchkrow GX [Ruler of the Night | Feather Storm | Unfair GX]","557470":"Whimsicott GX [Fluffy Cotton | Energy Blow | Toy Box GX]","557471":"Persian GX [Cat Walk | Vengeance | Slash Back GX]","557472":"Fire Crystal","557473":"Shrine of Punishment","557474":"Triple Acceleration Energy"},"metrics":["avg","low","trend"]}
