{"id":"hs-trainer-kit-singles-universe","tcg":"pokemon","kind":"set-singles-universe","name":"HS Trainer Kit","slug":"hs-trainer-kit","source":{"productsCreatedAt":"2026-06-22T12:09:07+0200","idExpansion":1629,"cardmarketExpansionName":"HS Trainer Kit","cardmarketExpansionUrl":null,"cardmarketExpansionCardCount":null},"curation":{"status":"local-catalog-name-inferred","method":"idExpansion-product-ids-with-nonsingles-name-inference","cardmarketProductCount":60,"note":"Generated from Cardmarket product catalog idExpansion membership and non-single product names because the expansion page could not be fetched locally."},"count":60,"entries":{"279096":"Raichu [Iron Tail | Thunderbolt]","279097":"Lightning Energy","279098":"Pikachu [Tail Slap | Quick Attack]","279099":"Mareep [Static Electricity | Ram]","279100":"Pokémon Collector","279101":"Copycat","279102":"Flaaffy [Thunder Spear | Thundershock]","279103":"Pikachu [Tail Slap | Quick Attack]","279104":"Lightning Energy","279105":"Lightning Energy","279106":"Meowth [Pay Day | Dig Claws]","279107":"Mareep [Static Electricity | Ram]","279108":"Lightning Energy","279109":"Lightning Energy","279110":"Lightning Energy","279111":"Switch","279112":"Lightning Energy","279113":"Meowth [Pay Day | Dig Claws]","279114":"Lightning Energy","279115":"Lightning Energy","279116":"Lightning Energy","279117":"Lightning Energy","279118":"Raichu [Iron Tail | Thunderbolt]","279119":"Flaaffy [Thunder Spear | Thundershock]","279120":"Moomoo Milk","279121":"Poké Ball","279122":"Pokémon Collector","279123":"Lightning Energy","279124":"Energy Switch","279125":"Moomoo Milk","279126":"Water Energy","279127":"Bill","279128":"Croconaw [Wave Splash | Big Bite]","279129":"Magikarp [Splash | CL]","279130":"Water Energy","279131":"Energy Switch","279132":"Gyarados [Hydro Splash | Hyper Beam]","279133":"Water Energy","279134":"Marill [Water Splash | Tail Slap]","279135":"Water Energy","279136":"Water Energy","279137":"Magikarp [Splash | CL]","279138":"Croconaw [Wave Splash | Big Bite]","279139":"Totodile [Gnaw | Wave Splash]","279140":"Pokémon Communication","279141":"Poké Ball","279142":"Water Energy","279143":"Gyarados [Hydro Splash | Hyper Beam]","279144":"Bill","279145":"Water Energy","279146":"Water Energy","279147":"Water Energy","279148":"Water Energy","279149":"Water Energy","279150":"Professor Elm's Training Method","279151":"Marill [Water Splash | Tail Slap]","279152":"Water Energy","279153":"Pokémon Communication","279154":"Switch","279155":"Totodile [Gnaw | Wave Splash]"},"metrics":["avg","low","trend"]}
