{"id":"paradise-dragona-singles-universe","tcg":"pokemon","kind":"set-singles-universe","name":"Paradise Dragona","slug":"paradise-dragona","source":{"productsCreatedAt":"2026-06-22T12:09:07+0200","idExpansion":5846,"cardmarketExpansionName":"Paradise Dragona","cardmarketExpansionUrl":null,"cardmarketExpansionCardCount":null},"curation":{"status":"local-catalog-name-inferred","method":"idExpansion-product-ids-with-nonsingles-name-inference","cardmarketProductCount":94,"note":"Generated from Cardmarket product catalog idExpansion membership and non-single product names because the expansion page could not be fetched locally."},"count":94,"entries":{"787561":"Exeggcute [Precocious Evolution]","787562":"Morelull [Attach]","787563":"Shiinotic [Calming Light | Spiral Rush]","787564":"Dhelmise [Rescue Kedge | Annihilating Anchor]","787565":"Zarude [Leaf Drain | Jungle Whip]","787566":"Castform Sunny Form [Singe | Sunny Assist]","787567":"Pansear [Combustion]","787568":"Simisear [Double Smash]","787569":"Gouging Fire [Lunge Out | Blazing Charge]","787570":"Cryogonal [Call Sign | Ice Beam]","787571":"Black Kyurem ex [Ice Age | Black Frost]","787572":"Bruxish [Counterattack | Big Bite]","787573":"Quaxly [Aerial Ace]","787574":"Quaxwell [Aqua Edge]","787575":"Quaquaval [Uptempo | Hydro Splash]","787576":"Cetoddle [Draining Fin]","787577":"Cetitan [Solid Body | Dangerous Mouth]","787578":"Smoochum [Delightful Kiss]","787579":"Latias ex [Skyliner | Eon Blade]","787580":"Latios [Skill Dive | Jet Headbutt]","787581":"Tapu Lele [Perplex | Mental Crush]","787582":"Flittle [Splashing Dodge]","787583":"Espathra [Mystical Eyes | Spiral Drain]","787584":"Gimmighoul [Minor Errand-Running | Tackle]","787585":"Trapinch [Call for Family | Bite]","787586":"Vibrava [Screech | Cutting Wind]","787587":"Flygon ex [Reversing Storm | Sonic Peridot]","787588":"Drilbur [Burrow | Mud-Slap]","787589":"Excadrill [Digging Claw | Drill Smash]","787590":"Landorus [Fist of Focus | Buster Swing]","787591":"Passimian [Coordinated Throwing]","787592":"Clobbopus [Slight Intrusion]","787593":"Grapploct [Chop | Raging Tentacles]","787594":"Skarmory [Steel Wing]","787595":"Klefki [Stick 'n' Draw | Hook]","787596":"Duraludon [Confront | Duralubeam]","787597":"Archaludon ex [Assemble Alloy | Metal Defender]","787598":"Gholdengo [Strike It Rich | Surf Back]","787599":"Iron Crown [Deleting Slash | Slicing Blade]","787600":"Alolan Exeggutor ex [Tropical Frenzy | Swinging Sphene]","787601":"Altaria [Humming Charge | Cotton Wings]","787602":"Dialga [Time Manipulation | Buster Tail]","787603":"Palkia [Space Crash]","787604":"Turtonator [Fully Singe | Steaming Stomp]","787605":"Applin [Nutrients | Trip Over]","787606":"Flapple [Acidic Spit | Speed Dive]","787607":"Appletun [Melting Sweetness | Wild Tackle]","787608":"Swablu [Disarming Voice]","787609":"Rufflet [Flap]","787610":"Braviary [Drag Off | Blasting Wind]","787611":"Cyclizar ex [Break Through | Zircon Road]","787612":"Energy Search Pro","787613":"Call Bell","787614":"Dusk Ball","787615":"Meddling Memo","787616":"Megaton Blower","787617":"Dragon Elixir","787618":"Passho Berry","787619":"Counter Gain","787620":"Drayton","787621":"Surfer","787622":"Drasna","787623":"Lisia's Appeal","787624":"Enriching Energy","788038":"Exeggcute [Precocious Evolution]","788039":"Shiinotic [Calming Light | Spiral Rush]","788040":"Castform Sunny Form [Singe | Sunny Assist]","788041":"Bruxish [Counterattack | Big Bite]","788042":"Cetitan [Solid Body | Dangerous Mouth]","788043":"Latios [Skill Dive | Jet Headbutt]","788044":"Vibrava [Screech | Cutting Wind]","788045":"Clobbopus [Slight Intrusion]","788046":"Skarmory [Steel Wing]","788047":"Flapple [Acidic Spit | Speed Dive]","788048":"Appletun [Melting Sweetness | Wild Tackle]","788049":"Braviary [Drag Off | Blasting Wind]","788050":"Black Kyurem ex [Ice Age | Black Frost]","788051":"Latias ex [Skyliner | Eon Blade]","788052":"Flygon ex [Reversing Storm | Sonic Peridot]","788053":"Archaludon ex [Assemble Alloy | Metal Defender]","788054":"Alolan Exeggutor ex [Tropical Frenzy | Swinging Sphene]","788055":"Cyclizar ex [Break Through | Zircon Road]","788056":"Drayton","788057":"Surfer","788058":"Drasna","788059":"Lisia's Appeal","788060":"Latias ex [Skyliner | Eon Blade]","788061":"Archaludon ex [Assemble Alloy | Metal Defender]","788062":"Alolan Exeggutor ex [Tropical Frenzy | Swinging Sphene]","788063":"Drayton","788064":"Lisia's Appeal","788065":"Alolan Exeggutor ex [Tropical Frenzy | Swinging Sphene]","788066":"Counter Gain","788067":"Jet Energy"},"metrics":["avg","low","trend"]}
