{"id":"mega-dream-ex-additionals-singles-market","name":"MEGA Dream ex: Additionals Singles Market Weight","currency":"EUR","baseDate":"2026-06-23","baseValue":100,"updatedAt":"2026-06-25","metrics":["avg","low","trend"],"composition":{"universe":"mega-dream-ex-additionals-singles","universePolicy":"fixed-curated","universeFile":"/data/pokemon/universes/mega-dream-ex-additionals-singles-universe.json","method":"market","currentBaseDate":"2026-06-23","matchedProducts":236,"activeProductsByMetric":{"avg":32,"low":236,"trend":35},"missingProductsByMetric":{"avg":204,"low":0,"trend":201}},"diagnostics":{"2026-06-23":{"sourceCreatedAt":{"products":"2026-06-22T12:09:07+0200","prices":"2026-06-23T02:46:08+0200"},"quality":{"avg":{"matchedProducts":236,"pricedProducts":32,"missing":204,"carried":0,"activeProducts":32,"unavailable":0},"low":{"matchedProducts":236,"pricedProducts":236,"missing":0,"carried":0,"activeProducts":236,"unavailable":0},"trend":{"matchedProducts":236,"pricedProducts":35,"missing":201,"carried":0,"activeProducts":35,"unavailable":0}},"rebalance":false,"metricRebalances":{}},"2026-06-24":{"sourceCreatedAt":{"products":"2026-06-22T12:09:07+0200","prices":"2026-06-24T02:44:13+0200"},"quality":{"avg":{"matchedProducts":236,"pricedProducts":28,"missing":208,"carried":4,"activeProducts":32,"unavailable":0},"low":{"matchedProducts":236,"pricedProducts":236,"missing":0,"carried":0,"activeProducts":236,"unavailable":0},"trend":{"matchedProducts":236,"pricedProducts":35,"missing":201,"carried":0,"activeProducts":35,"unavailable":0}},"rebalance":false,"metricRebalances":{}},"2026-06-25":{"sourceCreatedAt":{"products":"2026-06-22T12:09:07+0200","prices":"2026-06-25T02:45:43+0200"},"quality":{"avg":{"matchedProducts":236,"pricedProducts":27,"missing":209,"carried":5,"activeProducts":32,"unavailable":0},"low":{"matchedProducts":236,"pricedProducts":236,"missing":0,"carried":0,"activeProducts":236,"unavailable":0},"trend":{"matchedProducts":236,"pricedProducts":35,"missing":201,"carried":0,"activeProducts":35,"unavailable":0}},"rebalance":false,"metricRebalances":{}}},"points":[["2026-06-23",100,100,100],["2026-06-24",100,100,100],["2026-06-25",100,100.23,100]]}
