{"id":"tag-bolt-singles-market","name":"Tag Bolt Singles Market Weight","currency":"EUR","baseDate":"2026-06-23","baseValue":100,"updatedAt":"2026-06-24","metrics":["avg","low","trend"],"composition":{"universe":"tag-bolt-singles","universePolicy":"fixed-curated","universeFile":"/data/pokemon/universes/tag-bolt-singles-universe.json","method":"market","currentBaseDate":"2026-06-23","matchedProducts":118,"activeProductsByMetric":{"avg":118,"low":118,"trend":118},"missingProductsByMetric":{"avg":0,"low":0,"trend":0}},"diagnostics":{"2026-06-23":{"sourceCreatedAt":{"products":"2026-06-22T12:09:07+0200","prices":"2026-06-23T02:46:08+0200"},"quality":{"avg":{"matchedProducts":118,"pricedProducts":118,"missing":0,"carried":0,"activeProducts":118,"unavailable":0},"low":{"matchedProducts":118,"pricedProducts":118,"missing":0,"carried":0,"activeProducts":118,"unavailable":0},"trend":{"matchedProducts":118,"pricedProducts":118,"missing":0,"carried":0,"activeProducts":118,"unavailable":0}},"rebalance":false,"metricRebalances":{}},"2026-06-24":{"sourceCreatedAt":{"products":"2026-06-22T12:09:07+0200","prices":"2026-06-24T02:44:13+0200"},"quality":{"avg":{"matchedProducts":118,"pricedProducts":118,"missing":0,"carried":0,"activeProducts":118,"unavailable":0},"low":{"matchedProducts":118,"pricedProducts":118,"missing":0,"carried":0,"activeProducts":118,"unavailable":0},"trend":{"matchedProducts":118,"pricedProducts":118,"missing":0,"carried":0,"activeProducts":118,"unavailable":0}},"rebalance":false,"metricRebalances":{}}},"points":[["2026-06-23",100,100,100],["2026-06-24",122.18,100,99.94]]}
